numpiyy/Astar.py
numpiyy/BFS.py
numpiyy/DFID.py
numpiyy/DFS.py
numpiyy/Genetic.py
numpiyy/Hill_Climbing.py
numpiyy/Simulated_Annealing.py
numpiyy/UCS.py
numpiyy/__init__.py
numpiyy-0.1.dist-info/METADATA
numpiyy-0.1.dist-info/WHEEL
numpiyy-0.1.dist-info/top_level.txt
numpiyy-0.1.dist-info/RECORD
