Metadata-Version: 2.1
Name: numpiyy
Version: 0.1
Summary: A package for doing cool stuff
Home-page: UNKNOWN
Author: Your Name
Author-email: your@email.com
License: UNKNOWN
Platform: UNKNOWN
